{
 "cells": [
  {
   "cell_type": "code",
   "execution_count": 30,
   "metadata": {},
   "outputs": [],
   "source": [
    "def describe_func_closure(func):\n",
    "    print(func.__name__, ': ')\n",
    "    code = func.__code__\n",
    "    print('\\t cells: ', end='')\n",
    "    if func.__closure__ is not None:\n",
    "        for cell in func.__closure__:\n",
    "            print(cell.cell_contents, end=' ')\n",
    "    print()\n",
    "    for name in dir(code):\n",
    "        if name in ('co_cellvars', 'co_freevars'):\n",
    "            print('\\t', name, ': ', getattr(code, name))"
   ]
  },
  {
   "cell_type": "code",
   "execution_count": 37,
   "metadata": {},
   "outputs": [
    {
     "name": "stdout",
     "output_type": "stream",
     "text": [
      "foo : \n",
      "\t cells: \n",
      "\t co_cellvars :  ('x', 'y')\n",
      "\t co_freevars :  ()\n",
      "bar1 : \n",
      "\t cells: 1 \n",
      "\t co_cellvars :  ()\n",
      "\t co_freevars :  ('x',)\n",
      "bar2 : \n",
      "\t cells: 1 2 \n",
      "\t co_cellvars :  ()\n",
      "\t co_freevars :  ('x', 'y')\n"
     ]
    }
   ],
   "source": [
    "def foo():\n",
    "    x, y = (1, 2)\n",
    "    def bar1():\n",
    "        print(x)\n",
    "    \n",
    "    def bar2():\n",
    "        print(x, y)\n",
    "    \n",
    "    return bar1, bar2\n",
    "\n",
    "b1, b2 = foo()\n",
    "describe_func_closure(foo)\n",
    "describe_func_closure(b1)\n",
    "describe_func_closure(b2)"
   ]
  },
  {
   "cell_type": "code",
   "execution_count": 36,
   "metadata": {},
   "outputs": [
    {
     "name": "stdout",
     "output_type": "stream",
     "text": [
      "foo : \n",
      "\t cells: \n",
      "\t co_cellvars :  ('x',)\n",
      "\t co_freevars :  ()\n",
      "adder : \n",
      "\t cells: 1 \n",
      "\t co_cellvars :  ()\n",
      "\t co_freevars :  ('x',)\n",
      "printer : \n",
      "\t cells: 1 \n",
      "\t co_cellvars :  ()\n",
      "\t co_freevars :  ('x',)\n",
      "---------------------------\n",
      "adder()\n",
      "---------------------------\n",
      "adder : \n",
      "\t cells: 2 \n",
      "\t co_cellvars :  ()\n",
      "\t co_freevars :  ('x',)\n",
      "printer : \n",
      "\t cells: 2 \n",
      "\t co_cellvars :  ()\n",
      "\t co_freevars :  ('x',)\n",
      "---------------------------\n",
      "new\n",
      "---------------------------\n",
      "adder : \n",
      "\t cells: 1 \n",
      "\t co_cellvars :  ()\n",
      "\t co_freevars :  ('x',)\n",
      "printer : \n",
      "\t cells: 1 \n",
      "\t co_cellvars :  ()\n",
      "\t co_freevars :  ('x',)\n"
     ]
    }
   ],
   "source": [
    "def foo():\n",
    "    x = 1\n",
    "    def adder():\n",
    "        nonlocal x\n",
    "        x += 1\n",
    "    \n",
    "    def printer():\n",
    "        print(x)\n",
    "    \n",
    "    return adder, printer\n",
    "\n",
    "adder, printer = foo()\n",
    "describe_func_closure(foo)\n",
    "describe_func_closure(adder)\n",
    "describe_func_closure(printer)\n",
    "print('---------------------------')\n",
    "print('adder()')\n",
    "print('---------------------------')\n",
    "adder()\n",
    "describe_func_closure(adder)\n",
    "describe_func_closure(printer)\n",
    "print('---------------------------')\n",
    "print('new')\n",
    "print('---------------------------')\n",
    "adder, printer = foo()\n",
    "describe_func_closure(adder)\n",
    "describe_func_closure(printer)"
   ]
  },
  {
   "cell_type": "code",
   "execution_count": 41,
   "metadata": {},
   "outputs": [
    {
     "name": "stdout",
     "output_type": "stream",
     "text": [
      "2 2\n",
      "  4           0 LOAD_CONST               1 ((1, 2))\n",
      "              2 UNPACK_SEQUENCE          2\n",
      "              4 STORE_DEREF              0 (x)\n",
      "              6 STORE_DEREF              1 (y)\n",
      "\n",
      "  5           8 LOAD_CLOSURE             0 (x)\n",
      "             10 BUILD_TUPLE              1\n",
      "             12 LOAD_CONST               2 (<code object bar1 at 0x108c4f660, file \"/var/folders/90/l75jsw6n1_g9z2yr07xqwzcw0000gn/T/ipykernel_86181/1494465118.py\", line 5>)\n",
      "             14 LOAD_CONST               3 ('foo.<locals>.bar1')\n",
      "             16 MAKE_FUNCTION            8 (closure)\n",
      "             18 STORE_FAST               0 (bar1)\n",
      "\n",
      "  8          20 LOAD_CLOSURE             0 (x)\n",
      "             22 LOAD_CLOSURE             1 (y)\n",
      "             24 BUILD_TUPLE              2\n",
      "             26 LOAD_CONST               4 (<code object bar2 at 0x108c4f450, file \"/var/folders/90/l75jsw6n1_g9z2yr07xqwzcw0000gn/T/ipykernel_86181/1494465118.py\", line 8>)\n",
      "             28 LOAD_CONST               5 ('foo.<locals>.bar2')\n",
      "             30 MAKE_FUNCTION            8 (closure)\n",
      "             32 STORE_FAST               1 (bar2)\n",
      "\n",
      " 11          34 LOAD_DEREF               0 (x)\n",
      "             36 LOAD_CONST               6 (1)\n",
      "             38 INPLACE_ADD\n",
      "             40 STORE_DEREF              0 (x)\n",
      "\n",
      " 12          42 LOAD_GLOBAL              0 (print)\n",
      "             44 LOAD_DEREF               0 (x)\n",
      "             46 LOAD_DEREF               1 (y)\n",
      "             48 CALL_FUNCTION            2\n",
      "             50 POP_TOP\n",
      "\n",
      " 14          52 LOAD_FAST                0 (bar1)\n",
      "             54 LOAD_FAST                1 (bar2)\n",
      "             56 BUILD_TUPLE              2\n",
      "             58 RETURN_VALUE\n",
      "\n",
      "Disassembly of <code object bar1 at 0x108c4f660, file \"/var/folders/90/l75jsw6n1_g9z2yr07xqwzcw0000gn/T/ipykernel_86181/1494465118.py\", line 5>:\n",
      "  6           0 LOAD_GLOBAL              0 (print)\n",
      "              2 LOAD_DEREF               0 (x)\n",
      "              4 CALL_FUNCTION            1\n",
      "              6 POP_TOP\n",
      "              8 LOAD_CONST               0 (None)\n",
      "             10 RETURN_VALUE\n",
      "\n",
      "Disassembly of <code object bar2 at 0x108c4f450, file \"/var/folders/90/l75jsw6n1_g9z2yr07xqwzcw0000gn/T/ipykernel_86181/1494465118.py\", line 8>:\n",
      "  9           0 LOAD_GLOBAL              0 (print)\n",
      "              2 LOAD_DEREF               0 (x)\n",
      "              4 LOAD_DEREF               1 (y)\n",
      "              6 CALL_FUNCTION            2\n",
      "              8 POP_TOP\n",
      "             10 LOAD_CONST               0 (None)\n",
      "             12 RETURN_VALUE\n"
     ]
    }
   ],
   "source": [
    "\n",
    "import dis\n",
    "\n",
    "def foo():\n",
    "    x, y = (1, 2)\n",
    "    def bar1():\n",
    "        print(x)\n",
    "    \n",
    "    def bar2():\n",
    "        print(x, y)\n",
    "    \n",
    "    x += 1\n",
    "    print(x, y)\n",
    "    \n",
    "    return bar1, bar2\n",
    "\n",
    "b1, b2 = foo()\n",
    "dis.dis(foo)\n"
   ]
  },
  {
   "cell_type": "code",
   "execution_count": 49,
   "metadata": {},
   "outputs": [
    {
     "name": "stdout",
     "output_type": "stream",
     "text": [
      "1 1\n",
      "2 1\n",
      "  4           0 LOAD_CONST               1 (1)\n",
      "              2 STORE_DEREF              1 (y)\n",
      "\n",
      "  5           4 LOAD_GLOBAL              0 (print)\n",
      "              6 LOAD_DEREF               0 (x)\n",
      "              8 LOAD_DEREF               1 (y)\n",
      "             10 CALL_FUNCTION            2\n",
      "             12 POP_TOP\n",
      "\n",
      "  7          14 LOAD_CLOSURE             0 (x)\n",
      "             16 BUILD_TUPLE              1\n",
      "             18 LOAD_CONST               2 (<code object bar1 at 0x108c0bea0, file \"/var/folders/90/l75jsw6n1_g9z2yr07xqwzcw0000gn/T/ipykernel_86181/2439059404.py\", line 7>)\n",
      "             20 LOAD_CONST               3 ('foo.<locals>.bar1')\n",
      "             22 MAKE_FUNCTION            8 (closure)\n",
      "             24 STORE_FAST               1 (bar1)\n",
      "\n",
      " 10          26 LOAD_CLOSURE             0 (x)\n",
      "             28 LOAD_CLOSURE             1 (y)\n",
      "             30 BUILD_TUPLE              2\n",
      "             32 LOAD_CONST               4 (<code object bar2 at 0x108c0bdf0, file \"/var/folders/90/l75jsw6n1_g9z2yr07xqwzcw0000gn/T/ipykernel_86181/2439059404.py\", line 10>)\n",
      "             34 LOAD_CONST               5 ('foo.<locals>.bar2')\n",
      "             36 MAKE_FUNCTION            8 (closure)\n",
      "             38 STORE_FAST               2 (bar2)\n",
      "\n",
      " 19          40 LOAD_DEREF               0 (x)\n",
      "             42 LOAD_CONST               1 (1)\n",
      "             44 INPLACE_ADD\n",
      "             46 STORE_DEREF              0 (x)\n",
      "\n",
      " 20          48 LOAD_GLOBAL              0 (print)\n",
      "             50 LOAD_DEREF               0 (x)\n",
      "             52 LOAD_DEREF               1 (y)\n",
      "             54 CALL_FUNCTION            2\n",
      "             56 POP_TOP\n",
      "\n",
      " 22          58 LOAD_FAST                1 (bar1)\n",
      "             60 LOAD_FAST                2 (bar2)\n",
      "             62 BUILD_TUPLE              2\n",
      "             64 RETURN_VALUE\n",
      "\n",
      "Disassembly of <code object bar1 at 0x108c0bea0, file \"/var/folders/90/l75jsw6n1_g9z2yr07xqwzcw0000gn/T/ipykernel_86181/2439059404.py\", line 7>:\n",
      "  8           0 LOAD_GLOBAL              0 (print)\n",
      "              2 LOAD_DEREF               0 (x)\n",
      "              4 CALL_FUNCTION            1\n",
      "              6 POP_TOP\n",
      "              8 LOAD_CONST               0 (None)\n",
      "             10 RETURN_VALUE\n",
      "\n",
      "Disassembly of <code object bar2 at 0x108c0bdf0, file \"/var/folders/90/l75jsw6n1_g9z2yr07xqwzcw0000gn/T/ipykernel_86181/2439059404.py\", line 10>:\n",
      " 11           0 LOAD_GLOBAL              0 (print)\n",
      "              2 LOAD_DEREF               1 (x)\n",
      "              4 LOAD_DEREF               2 (y)\n",
      "              6 CALL_FUNCTION            2\n",
      "              8 POP_TOP\n",
      "\n",
      " 12          10 LOAD_CONST               1 (3)\n",
      "             12 STORE_DEREF              0 (z)\n",
      "\n",
      " 14          14 LOAD_CLOSURE             0 (z)\n",
      "             16 BUILD_TUPLE              1\n",
      "             18 LOAD_CONST               2 (<code object bar3 at 0x108c0b660, file \"/var/folders/90/l75jsw6n1_g9z2yr07xqwzcw0000gn/T/ipykernel_86181/2439059404.py\", line 14>)\n",
      "             20 LOAD_CONST               3 ('foo.<locals>.bar2.<locals>.bar3')\n",
      "             22 MAKE_FUNCTION            8 (closure)\n",
      "             24 STORE_FAST               0 (bar3)\n",
      "\n",
      " 17          26 LOAD_FAST                0 (bar3)\n",
      "             28 RETURN_VALUE\n",
      "\n",
      "Disassembly of <code object bar3 at 0x108c0b660, file \"/var/folders/90/l75jsw6n1_g9z2yr07xqwzcw0000gn/T/ipykernel_86181/2439059404.py\", line 14>:\n",
      " 15           0 LOAD_GLOBAL              0 (print)\n",
      "              2 LOAD_DEREF               0 (z)\n",
      "              4 CALL_FUNCTION            1\n",
      "              6 POP_TOP\n",
      "              8 LOAD_CONST               0 (None)\n",
      "             10 RETURN_VALUE\n"
     ]
    }
   ],
   "source": [
    "import dis\n",
    "\n",
    "def foo(x):\n",
    "    y = 1\n",
    "    print(x, y)\n",
    "\n",
    "    def bar1():\n",
    "        print(x)\n",
    "    \n",
    "    def bar2():\n",
    "        print(x, y)\n",
    "        z = 3\n",
    "\n",
    "        def bar3():\n",
    "            print(z)\n",
    "\n",
    "        return bar3\n",
    "    \n",
    "    x += 1\n",
    "    print(x, y)\n",
    "    \n",
    "    return bar1, bar2\n",
    "\n",
    "b1, b2 = foo(1)\n",
    "dis.dis(foo)"
   ]
  },
  {
   "cell_type": "code",
   "execution_count": 46,
   "metadata": {},
   "outputs": [
    {
     "name": "stdout",
     "output_type": "stream",
     "text": [
      "1\n",
      "bar1 : \n",
      "\t cells: 1 \n",
      "\t co_cellvars :  ('z',)\n",
      "\t co_freevars :  ('x',)\n",
      "bar2 : \n",
      "\t cells: 1 2 \n",
      "\t co_cellvars :  ()\n",
      "\t co_freevars :  ('x', 'y')\n",
      "bar3 : \n",
      "\t cells: 3 \n",
      "\t co_cellvars :  ()\n",
      "\t co_freevars :  ('z',)\n",
      "foo : \n",
      "\t cells: \n",
      "\t co_cellvars :  ('x', 'y')\n",
      "\t co_freevars :  ()\n"
     ]
    },
    {
     "ename": "NameError",
     "evalue": "name 'z' is not defined",
     "output_type": "error",
     "traceback": [
      "\u001b[0;31m---------------------------------------------------------------------------\u001b[0m",
      "\u001b[0;31mNameError\u001b[0m                                 Traceback (most recent call last)",
      "Cell \u001b[0;32mIn[46], line 23\u001b[0m\n\u001b[1;32m     21\u001b[0m describe_func_closure(b3)\n\u001b[1;32m     22\u001b[0m describe_func_closure(foo)\n\u001b[0;32m---> 23\u001b[0m \u001b[39mprint\u001b[39m(z)\n",
      "\u001b[0;31mNameError\u001b[0m: name 'z' is not defined"
     ]
    }
   ],
   "source": [
    "def foo():\n",
    "    x, y = (1, 2)\n",
    "    def bar1():\n",
    "        z = 3 \n",
    "        print(x)\n",
    "        \n",
    "        def bar3():\n",
    "            print(z)\n",
    "        \n",
    "        return bar3\n",
    "    \n",
    "    def bar2():\n",
    "        print(x, y)\n",
    "    \n",
    "    return bar1, bar2\n",
    "\n",
    "b1, b2 = foo()\n",
    "b3 = b1()\n",
    "describe_func_closure(b1)\n",
    "describe_func_closure(b2)\n",
    "describe_func_closure(b3)\n",
    "describe_func_closure(foo)\n"
   ]
  },
  {
   "cell_type": "code",
   "execution_count": 50,
   "metadata": {},
   "outputs": [
    {
     "name": "stdout",
     "output_type": "stream",
     "text": [
      "  2           0 LOAD_CONST               1 (2)\n",
      "              2 STORE_DEREF              1 (y)\n",
      "\n",
      "  3           4 LOAD_CLOSURE             0 (x)\n",
      "              6 LOAD_CLOSURE             1 (y)\n",
      "              8 BUILD_TUPLE              2\n",
      "             10 LOAD_CONST               2 (<code object bar at 0x101b847c0, file \"/var/folders/90/l75jsw6n1_g9z2yr07xqwzcw0000gn/T/ipykernel_86181/1646305308.py\", line 3>)\n",
      "             12 LOAD_CONST               3 ('foo.<locals>.bar')\n",
      "             14 MAKE_FUNCTION            8 (closure)\n",
      "             16 STORE_FAST               1 (bar)\n",
      "\n",
      "  7          18 LOAD_FAST                1 (bar)\n",
      "             20 RETURN_VALUE\n",
      "\n",
      "Disassembly of <code object bar at 0x101b847c0, file \"/var/folders/90/l75jsw6n1_g9z2yr07xqwzcw0000gn/T/ipykernel_86181/1646305308.py\", line 3>:\n",
      "  5           0 LOAD_GLOBAL              0 (print)\n",
      "              2 LOAD_DEREF               0 (x)\n",
      "              4 LOAD_DEREF               1 (y)\n",
      "              6 CALL_FUNCTION            2\n",
      "              8 POP_TOP\n",
      "\n",
      "  6          10 LOAD_DEREF               1 (y)\n",
      "             12 LOAD_CONST               1 (1)\n",
      "             14 INPLACE_ADD\n",
      "             16 STORE_DEREF              1 (y)\n",
      "             18 LOAD_CONST               0 (None)\n",
      "             20 RETURN_VALUE\n"
     ]
    }
   ],
   "source": [
    "def foo(x):\n",
    "    y = 2\n",
    "    def bar():\n",
    "        nonlocal y\n",
    "        print(x, y)\n",
    "        y += 1\n",
    "    return bar\n",
    "\n",
    "dis.dis(foo)"
   ]
  },
  {
   "cell_type": "code",
   "execution_count": null,
   "metadata": {},
   "outputs": [],
   "source": []
  }
 ],
 "metadata": {
  "kernelspec": {
   "display_name": "Python 3",
   "language": "python",
   "name": "python3"
  },
  "language_info": {
   "codemirror_mode": {
    "name": "ipython",
    "version": 3
   },
   "file_extension": ".py",
   "mimetype": "text/x-python",
   "name": "python",
   "nbconvert_exporter": "python",
   "pygments_lexer": "ipython3",
   "version": "3.9.10 (main, Nov 21 2022, 16:25:07) \n[Clang 14.0.0 (clang-1400.0.29.202)]"
  },
  "orig_nbformat": 4,
  "vscode": {
   "interpreter": {
    "hash": "130bacdf9573dc7193b334a08cc93abf39ecb586813303fa9a27b089a9b8e574"
   }
  }
 },
 "nbformat": 4,
 "nbformat_minor": 2
}
